{
  "schemaVersion": 3,
  "framework": "vue",
  "package": "@acoyfellow/kumo-vue@0.0.1",
  "sourceTree": "209de54a856d0b900b32685434ffbb98a42b5d8c",
  "sourceTreeDigest": "4cd9b26190e00766102fc0af7532bd0adb699de52e20c54de6f0f15129ac39a0",
  "packageSha256": "dcfc1864096a12eabeacb73b3a37186d49e8668ee48245c07b440e691a742a4f",
  "deterministicRuns": 2,
  "versions": {
    "node": "v24.17.0",
    "npm": "11.13.0",
    "vite": "vite/8.0.16 darwin-arm64 node-<normalized>"
  },
  "commands": [
    "npm pack (twice)",
    "package file audit",
    "fresh tgz npm install",
    "all 41 root/subpath TypeScript imports",
    "Vite client build",
    "Vue SSR build/render",
    "66 packed semantic SSR comparisons",
    "compound export imports",
    "CSS/assets file presence",
    "Vite tree-shaking build",
    "npm workspace build"
  ],
  "exportSurface": {
    "componentCount": 41,
    "compoundPathCount": 63,
    "modelBindings": "passed",
    "compoundPaths": "passed",
    "rootImports": "passed",
    "subpathImports": "passed",
    "types": "passed",
    "noWorkspaceImports": "passed",
    "fileAudit": "passed",
    "treeShaking": "passed"
  },
  "packageConformance": {
    "clientBuild": "passed",
    "ssrBuild": "passed",
    "renderToString": "passed",
    "cssAssetsPresent": "passed"
  },
  "browserConformance": {
    "hydration": "not-run",
    "serverNodeIdentity": "not-run",
    "buttonFieldBehavior": "not-run",
    "hmr": "not-run",
    "screenReader": "not-run"
  },
  "staticSemanticConformance": {
    "status": "passed",
    "passed": 66,
    "unresolved": 0
  },
  "pendingReasons": {
    "hydration": "requires scripts/observable-browser-runner.mjs trusted conformance",
    "serverNodeIdentity": "requires scripts/observable-browser-runner.mjs trusted conformance",
    "buttonFieldBehavior": "requires scripts/observable-browser-runner.mjs trusted conformance",
    "hmr": "requires scripts/observable-browser-runner.mjs trusted conformance",
    "screenReader": "requires scripts/observable-browser-runner.mjs trusted conformance"
  },
  "observations": {},
  "receiptHash": "db1df864a3e6b00bce4444f7e08c3c9ca2520f2f65487458a46d71ff7981196d"
}
