{"ir":{"frontendFacts":{"oxc":{"classExpressions":[{"expressionType":"CallExpression","provenance":{"end":{"column":8939,"line":1,"offset":8938},"start":{"column":8786,"line":1,"offset":8785}}},{"expressionType":"Literal","provenance":{"end":{"column":9235,"line":1,"offset":9234},"start":{"column":9215,"line":1,"offset":9214}}},{"expressionType":"CallExpression","provenance":{"end":{"column":10005,"line":1,"offset":10004},"start":{"column":9808,"line":1,"offset":9807}}},{"expressionType":"CallExpression","provenance":{"end":{"column":10944,"line":1,"offset":10943},"start":{"column":10801,"line":1,"offset":10800}}}],"conditions":[{"provenance":{"end":{"column":4657,"line":1,"offset":4656},"start":{"column":4617,"line":1,"offset":4616}},"type":"LogicalExpression"},{"provenance":{"end":{"column":5595,"line":1,"offset":5594},"start":{"column":5441,"line":1,"offset":5440}},"type":"LogicalExpression"},{"provenance":{"end":{"column":5782,"line":1,"offset":5781},"start":{"column":5750,"line":1,"offset":5749}},"type":"IfStatement"},{"provenance":{"end":{"column":5847,"line":1,"offset":5846},"start":{"column":5785,"line":1,"offset":5784}},"type":"IfStatement"},{"provenance":{"end":{"column":8906,"line":1,"offset":8905},"start":{"column":8863,"line":1,"offset":8862}},"type":"LogicalExpression"},{"provenance":{"end":{"column":8977,"line":1,"offset":8976},"start":{"column":8958,"line":1,"offset":8957}},"type":"LogicalExpression"},{"provenance":{"end":{"column":9009,"line":1,"offset":9008},"start":{"column":8993,"line":1,"offset":8992}},"type":"LogicalExpression"},{"provenance":{"end":{"column":9178,"line":1,"offset":9177},"start":{"column":9051,"line":1,"offset":9050}},"type":"ConditionalExpression"},{"provenance":{"end":{"column":9110,"line":1,"offset":9109},"start":{"column":9087,"line":1,"offset":9086}},"type":"ConditionalExpression"},{"provenance":{"end":{"column":9253,"line":1,"offset":9252},"start":{"column":9189,"line":1,"offset":9188}},"type":"LogicalExpression"},{"provenance":{"end":{"column":9359,"line":1,"offset":9358},"start":{"column":9283,"line":1,"offset":9282}},"type":"IfStatement"},{"provenance":{"end":{"column":9916,"line":1,"offset":9915},"start":{"column":9880,"line":1,"offset":9879}},"type":"LogicalExpression"},{"provenance":{"end":{"column":10697,"line":1,"offset":10696},"start":{"column":10621,"line":1,"offset":10620}},"type":"ConditionalExpression"},{"provenance":{"end":{"column":11020,"line":1,"offset":11019},"start":{"column":10977,"line":1,"offset":10976}},"type":"ConditionalExpression"}],"defaults":[{"provenance":{"end":{"column":4588,"line":1,"offset":4587},"start":{"column":4415,"line":1,"offset":4414}},"target":"ObjectPattern","valueType":"ObjectExpression"},{"provenance":{"end":{"column":4465,"line":1,"offset":4464},"start":{"column":4419,"line":1,"offset":4418}},"target":"variant","valueType":"MemberExpression"},{"provenance":{"end":{"column":4509,"line":1,"offset":4508},"start":{"column":4469,"line":1,"offset":4468}},"target":"size","valueType":"MemberExpression"},{"provenance":{"end":{"column":4555,"line":1,"offset":4554},"start":{"column":4513,"line":1,"offset":4512}},"target":"shape","valueType":"MemberExpression"},{"provenance":{"end":{"column":8514,"line":1,"offset":8513},"start":{"column":8500,"line":1,"offset":8499}},"target":"shape","valueType":"Literal"},{"provenance":{"end":{"column":8535,"line":1,"offset":8534},"start":{"column":8522,"line":1,"offset":8521}},"target":"size","valueType":"Literal"},{"provenance":{"end":{"column":8564,"line":1,"offset":8563},"start":{"column":8543,"line":1,"offset":8542}},"target":"variant","valueType":"Literal"},{"provenance":{"end":{"column":9676,"line":1,"offset":9675},"start":{"column":9655,"line":1,"offset":9654}},"target":"ariaLabel","valueType":"Literal"},{"provenance":{"end":{"column":10402,"line":1,"offset":10401},"start":{"column":10388,"line":1,"offset":10387}},"target":"shape","valueType":"Literal"},{"provenance":{"end":{"column":10423,"line":1,"offset":10422},"start":{"column":10410,"line":1,"offset":10409}},"target":"size","valueType":"Literal"},{"provenance":{"end":{"column":10448,"line":1,"offset":10447},"start":{"column":10431,"line":1,"offset":10430}},"target":"variant","valueType":"Literal"}],"jsxElements":[{"attributes":[],"name":"Comp","provenance":{"end":{"column":5943,"line":1,"offset":5942},"start":{"column":5935,"line":1,"offset":5934}}},{"attributes":[{"expressionType":"Identifier","literal":null,"name":"ref"},{"expressionType":null,"literal":"Button","name":"data-kumo-component"},{"expressionType":"CallExpression","literal":null,"name":"className"},{"expressionType":"LogicalExpression","literal":null,"name":"disabled"},{"expressionType":"LogicalExpression","literal":null,"name":"type"},{"spread":"restProps"}],"name":"button","provenance":{"end":{"column":9270,"line":1,"offset":9269},"start":{"column":8715,"line":1,"offset":8714}}},{"attributes":[{"expressionType":"ConditionalExpression","literal":null,"name":"size"}],"name":"Loader","provenance":{"end":{"column":9114,"line":1,"offset":9113},"start":{"column":9073,"line":1,"offset":9072}}},{"attributes":[{"expressionType":null,"literal":"contents","name":"className"}],"name":"span","provenance":{"end":{"column":9253,"line":1,"offset":9252},"start":{"column":9209,"line":1,"offset":9208}}},{"attributes":[{"expressionType":"Identifier","literal":null,"name":"content"},{"expressionType":"Identifier","literal":null,"name":"render"}],"name":"Tooltip","provenance":{"end":{"column":9352,"line":1,"offset":9351},"start":{"column":9309,"line":1,"offset":9308}}},{"attributes":[{"expressionType":null,"literal":"square","name":"shape"},{"expressionType":"Identifier","literal":null,"name":"aria-label"},{"spread":"props"}],"name":"Button","provenance":{"end":{"column":10024,"line":1,"offset":10023},"start":{"column":9723,"line":1,"offset":9722}}},{"attributes":[{"expressionType":"CallExpression","literal":null,"name":"className"}],"name":"ArrowsClockwise","provenance":{"end":{"column":10012,"line":1,"offset":10011},"start":{"column":9785,"line":1,"offset":9784}}},{"attributes":[{"expressionType":"Identifier","literal":null,"name":"ref"},{"expressionType":null,"literal":"LinkButton","name":"data-kumo-component"},{"expressionType":"CallExpression","literal":null,"name":"className"},{"expressionType":"Identifier","literal":null,"name":"href"},{"expressionType":"ConditionalExpression","literal":null,"name":"to"},{"spread":"externalProps"},{"spread":"props"}],"name":"LinkComponent","provenance":{"end":{"column":11157,"line":1,"offset":11156},"start":{"column":10719,"line":1,"offset":10718}}}]},"typescript":{"branches":[{"condition":"o","kind":"BinaryExpression","provenance":{"column":5,"line":110}},{"condition":"s","kind":"ConditionalExpression","provenance":{"column":18,"line":117}},{"condition":"k.isValidElement(s)","kind":"ConditionalExpression","provenance":{"column":22,"line":117}},{"condition":"e","kind":"BinaryExpression","provenance":{"column":11,"line":137}},{"condition":"f","kind":"BinaryExpression","provenance":{"column":15,"line":141}},{"condition":"o","kind":"ConditionalExpression","provenance":{"column":11,"line":144}},{"condition":"r === \"lg\"","kind":"ConditionalExpression","provenance":{"column":44,"line":144}},{"condition":"s != null","kind":"BinaryExpression","provenance":{"column":11,"line":145}},{"condition":"i","kind":"ConditionalExpression","provenance":{"column":12,"line":149}},{"condition":"e","kind":"ConditionalExpression","provenance":{"column":24,"line":180}},{"condition":"typeof o == \"string\"","kind":"ConditionalExpression","provenance":{"column":13,"line":192}}],"classExpressions":[{"expression":"l(\n          v({ variant: m, size: r, shape: d }),\n          e && \"cursor-not-allowed opacity-50\",\n          t\n        )","provenance":{"column":9,"line":135},"staticTokens":["cursor-not-allowed","opacity-50"]},{"expression":"\"contents\"","provenance":{"column":52,"line":145},"staticTokens":["contents"]},{"expression":"l({\n      \"animate-refresh\": t,\n      \"size-4.5\": e.size === \"base\" || !e.size,\n      \"size-4\": e.size === \"sm\",\n      \"size-5\": e.size === \"lg\"\n    })","provenance":{"column":5,"line":160},"staticTokens":["animate-refresh","size-4.5","base","size-4","sm","size-5","lg"]},{"expression":"l(\n          v({ variant: m, size: r, shape: d }),\n          \"flex items-center no-underline!\",\n          t\n        )","provenance":{"column":9,"line":186},"staticTokens":["flex","items-center","no-underline!"]}],"defaults":[{"parameter":"s","provenance":{"column":3,"line":81},"value":"a.variant"},{"parameter":"t","provenance":{"column":3,"line":82},"value":"a.size"},{"parameter":"e","provenance":{"column":3,"line":83},"value":"a.shape"},{"parameter":"d","provenance":{"column":5,"line":123},"value":"base"},{"parameter":"r","provenance":{"column":5,"line":124},"value":"base"},{"parameter":"m","provenance":{"column":5,"line":125},"value":"secondary"},{"parameter":"s","provenance":{"column":3,"line":154},"value":"Refresh"},{"parameter":"d","provenance":{"column":5,"line":173},"value":"base"},{"parameter":"r","provenance":{"column":5,"line":174},"value":"base"},{"parameter":"m","provenance":{"column":5,"line":175},"value":"ghost"}],"structure":[{"attributes":[],"childSlots":0,"provenance":{"column":64,"line":117},"target":"s"},{"attributes":["...w","className","data-kumo-component","disabled","ref","type"],"childSlots":2,"provenance":{"column":54,"line":130},"target":"\"button\""},{"attributes":["size"],"childSlots":0,"provenance":{"column":31,"line":144},"target":"N"},{"attributes":["className"],"childSlots":1,"provenance":{"column":40,"line":145},"target":"\"span\""},{"attributes":["content","render"],"childSlots":0,"provenance":{"column":32,"line":149},"target":"L"},{"attributes":["...e","aria-label","shape"],"childSlots":1,"provenance":{"column":23,"line":157},"target":"z"},{"attributes":["className"],"childSlots":0,"provenance":{"column":96,"line":157},"target":"B"},{"attributes":["...f","...i","className","data-kumo-component","href","ref","to"],"childSlots":2,"provenance":{"column":28,"line":181},"target":"g"}]}},"source":{"oxc":{"path":"node_modules/@cloudflare/kumo/dist/chunks/button-ov39dxshqbqrthhd.js.map#sourcesContent[0]","sha256":"ced65cc8cc95cbade555e7feebf5bfd0189b99699f74171a072f4b02a10bb0eb"},"typescript":{"package":"@cloudflare/kumo","path":"node_modules/@cloudflare/kumo/dist/chunks/button-ov39dxshqbqrthhd.js","sha256":"09d11a49c39df6697987fa73b62c8efc60fdd5ffcd65484bcd8695f4dcf75d87","version":"2.5.2"}},"traces":[{"path":"tracer/artifacts/button/default/390/trace.json","screenshotSha256":"4b95d34a640637ffa4c3dd1903f03da55d6a1c2c00b0beea4343d047d2e67a8b","sha256":"7eefbe95c37134d03aba1abb676068ebbcfdc14d7ec256e8ef4fabfab222b1b5","state":"default","viewport":390},{"path":"tracer/artifacts/button/default/768/trace.json","screenshotSha256":"40784dfa9f5deb463de7217bdd0a0ec120c4d2f7ba0483f153dadd67aa768bcf","sha256":"8883c1b7a0e3d93c59d7573bd755d8aeaccf01411e291ad96a3e32896b8bee05","state":"default","viewport":768},{"path":"tracer/artifacts/button/default/1440/trace.json","screenshotSha256":"d8f203bae3a8e5931e61d191c3e4abded5438b8a4e657d418385d1b6da3adcbc","sha256":"78507cf7e6b3608ead7e8bafa079a9a1fc339e98dbe9fd56f46533e16267e33f","state":"default","viewport":1440},{"path":"tracer/artifacts/button/disabled/390/trace.json","screenshotSha256":"2dbf4445c62bebdccb5d0f565e53b29602b1a626ceb1b91e558f99fdc49e16e7","sha256":"d636d014cf715f62ad8889274133216fd7e9e22de3d305eed4352a0764be701d","state":"disabled","viewport":390},{"path":"tracer/artifacts/button/disabled/768/trace.json","screenshotSha256":"7c7a4e581c708dca757246ef3e8c72beb50cff24884482df547f98c8a8ab191e","sha256":"2b789771190b8b88ac301b25ba93b1c6a48e93798e6dca587dcb3a1b64768f85","state":"disabled","viewport":768},{"path":"tracer/artifacts/button/disabled/1440/trace.json","screenshotSha256":"88b18e5b508a4608e3806e1e1a9d34c7194a34e158ae1ab31f95fb26597bed31","sha256":"ac059bf40e720885b47bfa1517df2cdc3834304d9015779123bbf97bf2e20319","state":"disabled","viewport":1440},{"path":"tracer/artifacts/button/loading/390/trace.json","screenshotSha256":"8bc4df1ef1fe831f3bb53f744bf20da323761e48892c9c19fb721e983f76a530","sha256":"548c34ec404e21a6926062e013c4d3b814d7d84b88941b931793086a08725f30","state":"loading","viewport":390},{"path":"tracer/artifacts/button/loading/768/trace.json","screenshotSha256":"00d4b0c8c38357b43c0ba1720097351fef244a9bef4fb16816f4e5727aa8e83e","sha256":"7bfb5228fea6d4db6883811778bd1ebdc0e9cdfa06d86bd2f5810af5a26b0569","state":"loading","viewport":768},{"path":"tracer/artifacts/button/loading/1440/trace.json","screenshotSha256":"7bc2305b605991b558f71455a00b2e88094048fb6dbef7ddbb6d101397169f06","sha256":"6f861719aab6c39f2a6ee930a35e0d587b95e691a081997194af6b6161a97a2b","state":"loading","viewport":1440}]},"lowerer":{"path":"lowering/vue/lower.mjs","sha256":"8a129dfb8fc7041046456ef92e8219341c3fb15211956670622c631116c58b54"},"plan":{"contentDigest":"b4e6eb8d9a79669c39fa6cc74e3c6b0d898ab20fb505151ea04972cedc25e1f9","manifestDigest":"2c71b8c47de5f2040f3b8e2009dd950c1bd722acf91d6c2d08f8e9586d08f989","schemaVersion":"kumo.lowering-plan/v1","shard":"sha256-b4e6eb8d9a79669c39fa6cc74e3c6b0d898ab20fb505151ea04972cedc25e1f9.json"},"schemaVersion":"kumo.vue-provenance/v2","source":{"descriptor":{"id":"part-first","path":"ir/candidates/part-first.json","sha256":"06b4cdc745c9511627f9027e0ae34249dc0e5c61068938e6a73d2b9be18bce8b"},"ir":{"path":"ir/fixtures/components.json","schemaVersion":"kumo.core-ir/v2","sha256":"50f552bab895eb24f4efcefcabec78e41ffbac26f75b0fc2b47f1ce4b9527b96"},"lowerer":{"path":"lowering/vue/lower.mjs","sha256":"8a129dfb8fc7041046456ef92e8219341c3fb15211956670622c631116c58b54"}}}
