{
  "schemaVersion": "kumo.canonical-build/v1",
  "results": [
    {
      "component": "select",
      "status": "passed"
    },
    {
      "component": "button",
      "status": "passed"
    },
    {
      "component": "dialog",
      "status": "failed",
      "error": "Error: dialog: vite build /Users/jcoeyman/cloudflare/kumo-compiler/runtime-canonical/dialog failed\n    at file:///Users/jcoeyman/cloudflare/kumo-compiler/scripts/build-canonical-react-runtimes.mjs:9:208"
    },
    {
      "component": "popover",
      "status": "failed",
      "error": "Error: popover: vite build /Users/jcoeyman/cloudflare/kumo-compiler/runtime-canonical/popover failed\n    at file:///Users/jcoeyman/cloudflare/kumo-compiler/scripts/build-canonical-react-runtimes.mjs:9:208"
    },
    {
      "component": "checkbox",
      "status": "passed"
    },
    {
      "component": "switch",
      "status": "passed"
    },
    {
      "component": "field",
      "status": "passed"
    },
    {
      "component": "input",
      "status": "passed"
    },
    {
      "component": "input-group",
      "status": "passed"
    },
    {
      "component": "input-area",
      "status": "passed"
    },
    {
      "component": "sensitive-input",
      "status": "passed"
    },
    {
      "component": "clipboard-text",
      "status": "passed"
    },
    {
      "component": "tabs",
      "status": "passed"
    },
    {
      "component": "menu-bar",
      "status": "passed"
    },
    {
      "component": "sidebar",
      "status": "passed"
    },
    {
      "component": "breadcrumbs",
      "status": "passed"
    },
    {
      "component": "table-of-contents",
      "status": "passed"
    },
    {
      "component": "badge",
      "status": "passed"
    },
    {
      "component": "banner",
      "status": "passed"
    },
    {
      "component": "surface",
      "status": "passed"
    },
    {
      "component": "layer-card",
      "status": "passed"
    },
    {
      "component": "grid",
      "status": "passed"
    },
    {
      "component": "grid-item",
      "status": "passed"
    },
    {
      "component": "loader",
      "status": "passed"
    },
    {
      "component": "meter",
      "status": "passed"
    },
    {
      "component": "empty",
      "status": "passed"
    },
    {
      "component": "label",
      "status": "passed"
    },
    {
      "component": "link",
      "status": "passed"
    },
    {
      "component": "text",
      "status": "passed"
    },
    {
      "component": "cloudflare-logo",
      "status": "passed"
    },
    {
      "component": "code",
      "status": "passed"
    },
    {
      "component": "table",
      "status": "passed"
    },
    {
      "component": "radio",
      "status": "passed"
    },
    {
      "component": "autocomplete",
      "status": "passed"
    },
    {
      "component": "combobox",
      "status": "passed"
    },
    {
      "component": "command-palette",
      "status": "passed"
    },
    {
      "component": "date-picker",
      "status": "passed"
    },
    {
      "component": "date-range-picker",
      "status": "passed"
    },
    {
      "component": "dropdown-menu",
      "status": "passed"
    },
    {
      "component": "toasty",
      "status": "passed"
    },
    {
      "component": "pagination",
      "status": "passed"
    }
  ]
}
