{
  "schemaVersion": "kumo.receipt/v1",
  "component": "clipboard-text",
  "framework": "solid",
  "checks": {
    "productionBuild": true,
    "network": true,
    "console": true,
    "domAria": true,
    "behavior": true,
    "ssrHydration": true,
    "screenshotPixel": true,
    "assetsStylesPackage": true,
    "provenance": true
  },
  "browser": {
    "before": "npm i kumo",
    "after": "browser proof",
    "focused": true,
    "type": "text",
    "pressed": null,
    "status": "",
    "required": false,
    "hydration": true
  },
  "screenshotHash": "ccdfda3780f1d1315003819161b87779bd81a45a9ab905264eafda1eef7518bc",
  "irHash": "56db4334a5b0d2bb2954cc055ed85dab2ee70271e02fb34386568ff3956911f3",
  "emitterHash": "2bbb1898da30dc18ee8e8031eaa2351b4a5b18aa5390d326d60e0a7df29b2f80"
}
