{
  "schemaVersion": "kumo.receipt/v1",
  "component": "code",
  "framework": "vue",
  "checks": {
    "build": true,
    "runtime": true,
    "assets": true,
    "styles": true,
    "console": true,
    "dom": true,
    "aria": true,
    "behavior": true,
    "ssrHydration": true,
    "package": true,
    "screenshot": true,
    "nativeSfc": true,
    "provenance": true,
    "staticRules": true
  },
  "irHash": "22ecc836b3d465d4fd229b4faa55ead21e6e3dba403199ac1dda563306a4f35c",
  "emitterHash": "3767ef75dcd4eb42ba56bb7336873ecff70f9f157a7d5b19f147f36bfbad9b02"
}
