{
  "schemaVersion": "kumo.receipt/v1",
  "component": "input-area",
  "framework": "vue",
  "checks": {
    "build": true,
    "runtime": true,
    "assets": true,
    "styles": true,
    "console": true,
    "dom": true,
    "aria": true,
    "behavior": true,
    "ssrHydration": true,
    "package": true,
    "screenshot": true,
    "nativeSfc": true,
    "provenance": true,
    "staticRules": true
  },
  "irHash": "388521a42bbb7f2790f5798a9b3bff51d758dae30f2b3e3ecfdf67891aa86d7a",
  "emitterHash": "f00d239ca085397dd9fec48462aff98998da28790954ccdf5b9d23be4b9dabf3"
}
